aigov_libs/__init__.cpython-39-darwin.so
aigov_libs-1.1.6.data/data/APIs.md
aigov_libs-1.1.6.data/data/COPYRIGHT.txt
aigov_libs-1.1.6.data/data/VERSION.txt
cek_instr/__init__.cpython-39-darwin.so
cek_instr/cek_all.cpython-39-darwin.so
cek_instr/cek_builtins.cpython-39-darwin.so
cek_instr/cek_config.cpython-39-darwin.so
cek_instr/cek_import.cpython-39-darwin.so
cek_instr/cek_logging.cpython-39-darwin.so
cek_instr/cek_numpy.cpython-39-darwin.so
cek_instr/cek_pandas.cpython-39-darwin.so
cek_instr/cek_sklearn.cpython-39-darwin.so
cek_instr/cek_tracking.cpython-39-darwin.so
cek_instr/dependency.cpython-39-darwin.so
cek_instr/env2dk.cpython-39-darwin.so
cek_instr/ir.cpython-39-darwin.so
cek_instr/ir_func.cpython-39-darwin.so
cek_instr/repr_lambda.cpython-39-darwin.so
cek_instr/tracking.cpython-39-darwin.so
cek_instr/util.cpython-39-darwin.so
aigov_libs-1.1.6.dist-info/METADATA
aigov_libs-1.1.6.dist-info/WHEEL
aigov_libs-1.1.6.dist-info/top_level.txt
aigov_libs-1.1.6.dist-info/RECORD
