Metadata-Version: 2.1
Name: aigov-libs
Version: 1.1.6
Summary: aigov_libs
Author: IBM
License: UNKNOWN
Keywords: AI,Watson,IBM,AI Governance
Platform: UNKNOWN
Classifier: Programming Language :: Python :: 3
Classifier: License :: Other/Proprietary License
Classifier: Operating System :: OS Independent
Requires-Dist: timeout-decorator
Requires-Dist: astunparse
